pimped_subprocess/__init__.py
pimped_subprocess/capture_output.py
pimped_subprocess/pimped_subprocess_.py
pimped_subprocess-2.2.1.dist-info/DESCRIPTION.rst
pimped_subprocess-2.2.1.dist-info/METADATA
pimped_subprocess-2.2.1.dist-info/RECORD
pimped_subprocess-2.2.1.dist-info/WHEEL
pimped_subprocess-2.2.1.dist-info/metadata.json
pimped_subprocess-2.2.1.dist-info/top_level.txt
