Metadata-Version: 2.0
Name: pimped-subprocess
Version: 2.2.1
Summary: a pimped up subprocess module with monitoring and remote (SSH) capabilities
Home-page: https://github.com/haarcuba/pimped_subprocess
Author: Yoav Kleinberger
Author-email: haarcuba@gmail.com
License: UNKNOWN
Keywords: subprocess,terminal,monitoring
Platform: UNKNOWN
Classifier: Programming Language :: Python
Classifier: Operating System :: POSIX :: Linux
Provides-Extra: testing
Requires-Dist: pytest; extra == 'testing'
Requires-Dist: testix (==0.9); extra == 'testing'
